Metadata-Version: 1.1
Name: XComment
Version: 0.0.2
Summary: A script to remove comments from code.
Home-page: http://packages.python.org/XComment
Author: Singapore-Tech-Entrepreneurs
Author-email: tal@ste.sg
License: UNKNOWN
Keywords: code comments removal xcomment
Platform: UNKNOWN
Classifier: Development Status :: 3 - Alpha
Classifier: Topic :: Utilities
Classifier: Natural Language :: English
Classifier: Programming Language :: Python :: 3.6
